<?xml version='1.0' encoding='UTF-8' standalone='no'?>
<sbml xmlns="http://www.sbml.org/sbml/level3/version1/core" arrays:required="true" comp:required="true" fbc:required="false" layout:required="false" level="3" version="1" xmlns:arrays="http://www.sbml.org/sbml/level3/version1/arrays/version1" xmlns:comp="http://www.sbml.org/sbml/level3/version1/comp/version1" xmlns:fbc="http://www.sbml.org/sbml/level3/version1/fbc/version2" xmlns:layout="http://www.sbml.org/sbml/level3/version1/layout/version1">
  <comp:listOfExternalModelDefinitions xmlns:comp="http://www.sbml.org/sbml/level3/version1/comp/version1">
    <comp:externalModelDefinition comp:id="growth_fba" comp:source="growth_fba.xml"/>
    <comp:externalModelDefinition comp:id="growth_update" comp:source="growth_update.xml"/>
  </comp:listOfExternalModelDefinitions>
  <model fbc:strict="false" id="growth_top" metaid="iBioSim25">
    <comp:listOfSubmodels xmlns:comp="http://www.sbml.org/sbml/level3/version1/comp/version1">
      <comp:submodel comp:id="C1" comp:modelRef="growth_fba" metaid="iBioSim26"/>
      <comp:submodel comp:id="C2" comp:modelRef="growth_update" metaid="iBioSim29"/>
    </comp:listOfSubmodels>
    <comp:listOfPorts xmlns:comp="http://www.sbml.org/sbml/level3/version1/comp/version1">
      <comp:port comp:idRef="C1" id="compartment__Cell__C1" sboTerm="SBO:0000601">
        <comp:sBaseRef comp:portRef="compartment__Cell"/>
      </comp:port>
      <comp:port comp:idRef="C1" id="reaction__o_uptake__C1" sboTerm="SBO:0000601">
        <comp:sBaseRef comp:portRef="reaction__o_uptake"/>
      </comp:port>
      <comp:port comp:idRef="C1" id="reaction__g_uptake__C1" sboTerm="SBO:0000601">
        <comp:sBaseRef comp:portRef="reaction__g_uptake"/>
      </comp:port>
      <comp:port comp:idRef="C1" id="input__o_uptake_max__C1" sboTerm="SBO:0000600">
        <comp:sBaseRef comp:portRef="input__o_uptake_max"/>
      </comp:port>
      <comp:port comp:idRef="C2" id="compartment__Cell__C2" sboTerm="SBO:0000601">
        <comp:sBaseRef comp:portRef="compartment__Cell"/>
      </comp:port>
    </comp:listOfPorts>
    <layout:listOfLayouts xmlns:layout="http://www.sbml.org/sbml/level3/version1/layout/version1" xmlns:xsi="http://www.w3.org/2001/XMLSchema-instance">
      <layout:layout layout:id="iBioSim">
        <layout:dimensions layout:depth="0" layout:height="410" layout:width="810"/>
        <layout:listOfAdditionalGraphicalObjects>
          <layout:generalGlyph layout:id="Glyph__C1" layout:reference="C1">
            <layout:boundingBox>
              <layout:position layout:x="545" layout:y="10"/>
              <layout:dimensions layout:height="40" layout:width="80"/>
            </layout:boundingBox>
          </layout:generalGlyph>
          <layout:generalGlyph layout:id="Glyph__C2" layout:reference="C2">
            <layout:boundingBox>
              <layout:position layout:x="210" layout:y="170"/>
              <layout:dimensions layout:height="40" layout:width="80"/>
            </layout:boundingBox>
          </layout:generalGlyph>
          <layout:generalGlyph layout:id="Glyph__rateOfV1" layout:reference="rateOfV1">
            <layout:boundingBox>
              <layout:position layout:x="135" layout:y="260"/>
              <layout:dimensions layout:height="30" layout:width="30"/>
            </layout:boundingBox>
            <layout:listOfReferenceGlyphs>
              <layout:referenceGlyph layout:glyph="Glyph__R0" layout:id="Glyph__rateOfV1__product__R0" layout:role="product">
                <layout:curve>
                  <layout:listOfCurveSegments>
                    <layout:curveSegment xsi:type="LineSegment">
                      <layout:start layout:x="150" layout:y="275"/>
                      <layout:end layout:x="40" layout:y="120"/>
                    </layout:curveSegment>
                  </layout:listOfCurveSegments>
                </layout:curve>
              </layout:referenceGlyph>
            </layout:listOfReferenceGlyphs>
          </layout:generalGlyph>
          <layout:generalGlyph layout:id="Glyph__rateOfV2" layout:reference="rateOfV2">
            <layout:boundingBox>
              <layout:position layout:x="190" layout:y="260"/>
              <layout:dimensions layout:height="30" layout:width="30"/>
            </layout:boundingBox>
            <layout:listOfReferenceGlyphs>
              <layout:referenceGlyph layout:glyph="Glyph__R0" layout:id="Glyph__rateOfV2__product__R0" layout:role="product">
                <layout:curve>
                  <layout:listOfCurveSegments>
                    <layout:curveSegment xsi:type="LineSegment">
                      <layout:start layout:x="205" layout:y="275"/>
                      <layout:end layout:x="40" layout:y="120"/>
                    </layout:curveSegment>
                  </layout:listOfCurveSegments>
                </layout:curve>
              </layout:referenceGlyph>
            </layout:listOfReferenceGlyphs>
          </layout:generalGlyph>
          <layout:generalGlyph layout:id="Glyph__rateOfV3" layout:reference="rateOfV3">
            <layout:boundingBox>
              <layout:position layout:x="240" layout:y="260"/>
              <layout:dimensions layout:height="30" layout:width="30"/>
            </layout:boundingBox>
            <layout:listOfReferenceGlyphs>
              <layout:referenceGlyph layout:glyph="Glyph__R0" layout:id="Glyph__rateOfV3__product__R0" layout:role="product">
                <layout:curve>
                  <layout:listOfCurveSegments>
                    <layout:curveSegment xsi:type="LineSegment">
                      <layout:start layout:x="260" layout:y="275"/>
                      <layout:end layout:x="40" layout:y="120"/>
                    </layout:curveSegment>
                  </layout:listOfCurveSegments>
                </layout:curve>
              </layout:referenceGlyph>
            </layout:listOfReferenceGlyphs>
          </layout:generalGlyph>
          <layout:generalGlyph layout:id="Glyph__rateOfV4" layout:reference="rateOfV4">
            <layout:boundingBox>
              <layout:position layout:x="290" layout:y="260"/>
              <layout:dimensions layout:height="30" layout:width="30"/>
            </layout:boundingBox>
            <layout:listOfReferenceGlyphs>
              <layout:referenceGlyph layout:glyph="Glyph__R0" layout:id="Glyph__rateOfV4__product__R0" layout:role="product">
                <layout:curve>
                  <layout:listOfCurveSegments>
                    <layout:curveSegment xsi:type="LineSegment">
                      <layout:start layout:x="315" layout:y="275"/>
                      <layout:end layout:x="40" layout:y="120"/>
                    </layout:curveSegment>
                  </layout:listOfCurveSegments>
                </layout:curve>
              </layout:referenceGlyph>
            </layout:listOfReferenceGlyphs>
          </layout:generalGlyph>
          <layout:generalGlyph layout:id="Glyph__max_v1" layout:reference="max_v1">
            <layout:boundingBox>
              <layout:position layout:x="500" layout:y="70"/>
              <layout:dimensions layout:height="30" layout:width="30"/>
            </layout:boundingBox>
          </layout:generalGlyph>
          <layout:generalGlyph layout:id="Glyph__max_v2" layout:reference="max_v2">
            <layout:boundingBox>
              <layout:position layout:x="550" layout:y="70"/>
              <layout:dimensions layout:height="30" layout:width="30"/>
            </layout:boundingBox>
          </layout:generalGlyph>
          <layout:generalGlyph layout:id="Glyph__">
            <layout:boundingBox>
              <layout:position layout:x="60" layout:y="170"/>
              <layout:dimensions layout:height="30" layout:width="30"/>
            </layout:boundingBox>
          </layout:generalGlyph>
          <layout:generalGlyph layout:id="Glyph__max_v3" layout:reference="max_v3">
            <layout:boundingBox>
              <layout:position layout:x="600" layout:y="70"/>
              <layout:dimensions layout:height="30" layout:width="30"/>
            </layout:boundingBox>
          </layout:generalGlyph>
          <layout:generalGlyph layout:id="Glyph__max_v4" layout:reference="max_v4">
            <layout:boundingBox>
              <layout:position layout:x="650" layout:y="70"/>
              <layout:dimensions layout:height="30" layout:width="30"/>
            </layout:boundingBox>
          </layout:generalGlyph>
          <layout:generalGlyph layout:id="Glyph__g_rate_uptake" layout:reference="g_rate_uptake">
            <layout:boundingBox>
              <layout:position layout:x="340" layout:y="260"/>
              <layout:dimensions layout:height="30" layout:width="30"/>
            </layout:boundingBox>
          </layout:generalGlyph>
          <layout:generalGlyph layout:id="Glyph__g_uptake_max" layout:reference="g_uptake_max">
            <layout:boundingBox>
              <layout:position layout:x="375" layout:y="15"/>
              <layout:dimensions layout:height="30" layout:width="30"/>
            </layout:boundingBox>
          </layout:generalGlyph>
          <layout:generalGlyph layout:id="Glyph__rule0" layout:metaidRef="rule0">
            <layout:boundingBox>
              <layout:position layout:x="365" layout:y="100"/>
              <layout:dimensions layout:height="50" layout:width="50"/>
            </layout:boundingBox>
            <layout:listOfReferenceGlyphs>
              <layout:referenceGlyph layout:glyph="Glyph__Glcxt" layout:id="Glyph__rule0__substrate__Glcxt" layout:role="substrate">
                <layout:curve>
                  <layout:listOfCurveSegments>
                    <layout:curveSegment xsi:type="LineSegment">
                      <layout:start layout:x="390" layout:y="195"/>
                      <layout:end layout:x="390" layout:y="125"/>
                    </layout:curveSegment>
                  </layout:listOfCurveSegments>
                </layout:curve>
              </layout:referenceGlyph>
              <layout:referenceGlyph layout:glyph="Glyph__g_uptake_max" layout:id="Glyph__rule0__product__g_uptake_max" layout:role="product">
                <layout:curve>
                  <layout:listOfCurveSegments>
                    <layout:curveSegment xsi:type="LineSegment">
                      <layout:start layout:x="390" layout:y="125"/>
                      <layout:end layout:x="390" layout:y="30"/>
                    </layout:curveSegment>
                  </layout:listOfCurveSegments>
                </layout:curve>
              </layout:referenceGlyph>
            </layout:listOfReferenceGlyphs>
          </layout:generalGlyph>
          <layout:generalGlyph layout:id="Glyph__o_rate_uptake" layout:reference="o_rate_uptake">
            <layout:boundingBox>
              <layout:position layout:x="390" layout:y="260"/>
              <layout:dimensions layout:height="30" layout:width="30"/>
            </layout:boundingBox>
          </layout:generalGlyph>
          <layout:generalGlyph layout:id="Glyph__rule1" layout:metaidRef="rule1">
            <layout:boundingBox>
              <layout:position layout:x="130" layout:y="300"/>
              <layout:dimensions layout:height="50" layout:width="50"/>
            </layout:boundingBox>
            <layout:listOfReferenceGlyphs>
              <layout:referenceGlyph layout:glyph="Glyph__rateOfV1" layout:id="Glyph__rule1__product__rateOfV1" layout:role="product">
                <layout:curve>
                  <layout:listOfCurveSegments>
                    <layout:curveSegment xsi:type="LineSegment">
                      <layout:start layout:x="155" layout:y="325"/>
                      <layout:end layout:x="150" layout:y="275"/>
                    </layout:curveSegment>
                  </layout:listOfCurveSegments>
                </layout:curve>
              </layout:referenceGlyph>
            </layout:listOfReferenceGlyphs>
          </layout:generalGlyph>
          <layout:generalGlyph layout:id="Glyph__rule2" layout:metaidRef="rule2">
            <layout:boundingBox>
              <layout:position layout:x="180" layout:y="300"/>
              <layout:dimensions layout:height="50" layout:width="50"/>
            </layout:boundingBox>
            <layout:listOfReferenceGlyphs>
              <layout:referenceGlyph layout:glyph="Glyph__rateOfV2" layout:id="Glyph__rule2__product__rateOfV2" layout:role="product">
                <layout:curve>
                  <layout:listOfCurveSegments>
                    <layout:curveSegment xsi:type="LineSegment">
                      <layout:start layout:x="205" layout:y="325"/>
                      <layout:end layout:x="205" layout:y="275"/>
                    </layout:curveSegment>
                  </layout:listOfCurveSegments>
                </layout:curve>
              </layout:referenceGlyph>
            </layout:listOfReferenceGlyphs>
          </layout:generalGlyph>
          <layout:generalGlyph layout:id="Glyph__rule3" layout:metaidRef="rule3">
            <layout:boundingBox>
              <layout:position layout:x="230" layout:y="300"/>
              <layout:dimensions layout:height="50" layout:width="50"/>
            </layout:boundingBox>
            <layout:listOfReferenceGlyphs>
              <layout:referenceGlyph layout:glyph="Glyph__rateOfV3" layout:id="Glyph__rule3__product__rateOfV3" layout:role="product">
                <layout:curve>
                  <layout:listOfCurveSegments>
                    <layout:curveSegment xsi:type="LineSegment">
                      <layout:start layout:x="255" layout:y="325"/>
                      <layout:end layout:x="255" layout:y="275"/>
                    </layout:curveSegment>
                  </layout:listOfCurveSegments>
                </layout:curve>
              </layout:referenceGlyph>
            </layout:listOfReferenceGlyphs>
          </layout:generalGlyph>
          <layout:generalGlyph layout:id="Glyph__rule4" layout:metaidRef="rule4">
            <layout:boundingBox>
              <layout:position layout:x="280" layout:y="300"/>
              <layout:dimensions layout:height="50" layout:width="50"/>
            </layout:boundingBox>
            <layout:listOfReferenceGlyphs>
              <layout:referenceGlyph layout:glyph="Glyph__rateOfV4" layout:id="Glyph__rule4__product__rateOfV4" layout:role="product">
                <layout:curve>
                  <layout:listOfCurveSegments>
                    <layout:curveSegment xsi:type="LineSegment">
                      <layout:start layout:x="305" layout:y="325"/>
                      <layout:end layout:x="305" layout:y="275"/>
                    </layout:curveSegment>
                  </layout:listOfCurveSegments>
                </layout:curve>
              </layout:referenceGlyph>
            </layout:listOfReferenceGlyphs>
          </layout:generalGlyph>
          <layout:generalGlyph layout:id="Glyph__rule5" layout:metaidRef="rule5">
            <layout:boundingBox>
              <layout:position layout:x="330" layout:y="300"/>
              <layout:dimensions layout:height="50" layout:width="50"/>
            </layout:boundingBox>
            <layout:listOfReferenceGlyphs>
              <layout:referenceGlyph layout:glyph="Glyph__g_rate_uptake" layout:id="Glyph__rule5__product__g_rate_uptake" layout:role="product">
                <layout:curve>
                  <layout:listOfCurveSegments>
                    <layout:curveSegment xsi:type="LineSegment">
                      <layout:start layout:x="355" layout:y="325"/>
                      <layout:end layout:x="355" layout:y="275"/>
                    </layout:curveSegment>
                  </layout:listOfCurveSegments>
                </layout:curve>
              </layout:referenceGlyph>
            </layout:listOfReferenceGlyphs>
          </layout:generalGlyph>
          <layout:generalGlyph layout:id="Glyph__rule6" layout:metaidRef="rule6">
            <layout:boundingBox>
              <layout:position layout:x="380" layout:y="300"/>
              <layout:dimensions layout:height="50" layout:width="50"/>
            </layout:boundingBox>
            <layout:listOfReferenceGlyphs>
              <layout:referenceGlyph layout:glyph="Glyph__o_rate_uptake" layout:id="Glyph__rule6__product__o_rate_uptake" layout:role="product">
                <layout:curve>
                  <layout:listOfCurveSegments>
                    <layout:curveSegment xsi:type="LineSegment">
                      <layout:start layout:x="405" layout:y="325"/>
                      <layout:end layout:x="405" layout:y="275"/>
                    </layout:curveSegment>
                  </layout:listOfCurveSegments>
                </layout:curve>
              </layout:referenceGlyph>
            </layout:listOfReferenceGlyphs>
          </layout:generalGlyph>
        </layout:listOfAdditionalGraphicalObjects>
        <layout:listOfCompartmentGlyphs>
          <layout:compartmentGlyph layout:compartment="Cell" layout:id="Glyph__Cell">
            <layout:boundingBox>
              <layout:position layout:x="40" layout:y="0"/>
              <layout:dimensions layout:height="410" layout:width="770"/>
            </layout:boundingBox>
          </layout:compartmentGlyph>
        </layout:listOfCompartmentGlyphs>
        <layout:listOfSpeciesGlyphs>
          <layout:speciesGlyph layout:id="Glyph__O2" layout:species="O2">
            <layout:boundingBox>
              <layout:position layout:x="50" layout:y="180"/>
              <layout:dimensions layout:height="30" layout:width="100"/>
            </layout:boundingBox>
          </layout:speciesGlyph>
          <layout:speciesGlyph layout:id="Glyph__Ac" layout:species="Ac">
            <layout:boundingBox>
              <layout:position layout:x="120" layout:y="110"/>
              <layout:dimensions layout:height="30" layout:width="100"/>
            </layout:boundingBox>
          </layout:speciesGlyph>
          <layout:speciesGlyph layout:id="Glyph__Glcxt" layout:species="Glcxt">
            <layout:boundingBox>
              <layout:position layout:x="340" layout:y="180"/>
              <layout:dimensions layout:height="30" layout:width="100"/>
            </layout:boundingBox>
          </layout:speciesGlyph>
          <layout:speciesGlyph layout:id="Glyph__dummy" layout:species="dummy">
            <layout:boundingBox>
              <layout:position layout:x="220" layout:y="380"/>
              <layout:dimensions layout:height="30" layout:width="90"/>
            </layout:boundingBox>
          </layout:speciesGlyph>
          <layout:speciesGlyph layout:id="Glyph__X" layout:species="X">
            <layout:boundingBox>
              <layout:position layout:x="260" layout:y="110"/>
              <layout:dimensions layout:height="30" layout:width="100"/>
            </layout:boundingBox>
          </layout:speciesGlyph>
        </layout:listOfSpeciesGlyphs>
        <layout:listOfReactionGlyphs>
          <layout:reactionGlyph layout:id="Glyph__v1" layout:reaction="v1">
            <layout:boundingBox>
              <layout:position layout:x="145" layout:y="350"/>
              <layout:dimensions layout:height="20" layout:width="20"/>
            </layout:boundingBox>
            <layout:listOfSpeciesReferenceGlyphs>
              <layout:speciesReferenceGlyph layout:id="Glyph__v1__substrate__dummy" layout:role="substrate" layout:speciesGlyph="Glyph__dummy">
                <layout:curve>
                  <layout:listOfCurveSegments>
                    <layout:curveSegment xsi:type="LineSegment">
                      <layout:start layout:x="265" layout:y="395"/>
                      <layout:end layout:x="155" layout:y="360"/>
                    </layout:curveSegment>
                  </layout:listOfCurveSegments>
                </layout:curve>
              </layout:speciesReferenceGlyph>
            </layout:listOfSpeciesReferenceGlyphs>
          </layout:reactionGlyph>
          <layout:reactionGlyph layout:id="Glyph__v2" layout:reaction="v2">
            <layout:boundingBox>
              <layout:position layout:x="195" layout:y="350"/>
              <layout:dimensions layout:height="20" layout:width="20"/>
            </layout:boundingBox>
            <layout:listOfSpeciesReferenceGlyphs>
              <layout:speciesReferenceGlyph layout:id="Glyph__v2__substrate__dummy" layout:role="substrate" layout:speciesGlyph="Glyph__dummy">
                <layout:curve>
                  <layout:listOfCurveSegments>
                    <layout:curveSegment xsi:type="LineSegment">
                      <layout:start layout:x="265" layout:y="395"/>
                      <layout:end layout:x="205" layout:y="360"/>
                    </layout:curveSegment>
                  </layout:listOfCurveSegments>
                </layout:curve>
              </layout:speciesReferenceGlyph>
            </layout:listOfSpeciesReferenceGlyphs>
          </layout:reactionGlyph>
          <layout:reactionGlyph layout:id="Glyph__v3" layout:reaction="v3">
            <layout:boundingBox>
              <layout:position layout:x="250" layout:y="350"/>
              <layout:dimensions layout:height="20" layout:width="20"/>
            </layout:boundingBox>
            <layout:listOfSpeciesReferenceGlyphs>
              <layout:speciesReferenceGlyph layout:id="Glyph__v3__substrate__dummy" layout:role="substrate" layout:speciesGlyph="Glyph__dummy">
                <layout:curve>
                  <layout:listOfCurveSegments>
                    <layout:curveSegment xsi:type="LineSegment">
                      <layout:start layout:x="265" layout:y="395"/>
                      <layout:end layout:x="260" layout:y="360"/>
                    </layout:curveSegment>
                  </layout:listOfCurveSegments>
                </layout:curve>
              </layout:speciesReferenceGlyph>
            </layout:listOfSpeciesReferenceGlyphs>
          </layout:reactionGlyph>
          <layout:reactionGlyph layout:id="Glyph__v4" layout:reaction="v4">
            <layout:boundingBox>
              <layout:position layout:x="300" layout:y="350"/>
              <layout:dimensions layout:height="20" layout:width="20"/>
            </layout:boundingBox>
            <layout:listOfSpeciesReferenceGlyphs>
              <layout:speciesReferenceGlyph layout:id="Glyph__v4__substrate__dummy" layout:role="substrate" layout:speciesGlyph="Glyph__dummy">
                <layout:curve>
                  <layout:listOfCurveSegments>
                    <layout:curveSegment xsi:type="LineSegment">
                      <layout:start layout:x="265" layout:y="395"/>
                      <layout:end layout:x="310" layout:y="360"/>
                    </layout:curveSegment>
                  </layout:listOfCurveSegments>
                </layout:curve>
              </layout:speciesReferenceGlyph>
            </layout:listOfSpeciesReferenceGlyphs>
          </layout:reactionGlyph>
          <layout:reactionGlyph layout:id="Glyph__o2_transport" layout:reaction="o2_transport">
            <layout:boundingBox>
              <layout:position layout:x="90" layout:y="230"/>
              <layout:dimensions layout:height="20" layout:width="20"/>
            </layout:boundingBox>
            <layout:listOfSpeciesReferenceGlyphs>
              <layout:speciesReferenceGlyph layout:id="Glyph__o2_transport__product__O2" layout:role="product" layout:speciesGlyph="Glyph__O2">
                <layout:curve>
                  <layout:listOfCurveSegments>
                    <layout:curveSegment xsi:type="LineSegment">
                      <layout:start layout:x="100" layout:y="240"/>
                      <layout:end layout:x="100" layout:y="195"/>
                    </layout:curveSegment>
                  </layout:listOfCurveSegments>
                </layout:curve>
              </layout:speciesReferenceGlyph>
            </layout:listOfSpeciesReferenceGlyphs>
          </layout:reactionGlyph>
          <layout:reactionGlyph layout:id="Glyph__g_uptake" layout:reaction="g_uptake">
            <layout:boundingBox>
              <layout:position layout:x="340" layout:y="350"/>
              <layout:dimensions layout:height="20" layout:width="20"/>
            </layout:boundingBox>
            <layout:listOfSpeciesReferenceGlyphs>
              <layout:speciesReferenceGlyph layout:id="Glyph__g_uptake__substrate__dummy" layout:role="substrate" layout:speciesGlyph="Glyph__dummy">
                <layout:curve>
                  <layout:listOfCurveSegments>
                    <layout:curveSegment xsi:type="LineSegment">
                      <layout:start layout:x="265" layout:y="395"/>
                      <layout:end layout:x="350" layout:y="360"/>
                    </layout:curveSegment>
                  </layout:listOfCurveSegments>
                </layout:curve>
              </layout:speciesReferenceGlyph>
            </layout:listOfSpeciesReferenceGlyphs>
          </layout:reactionGlyph>
          <layout:reactionGlyph layout:id="Glyph__o_uptake" layout:reaction="o_uptake">
            <layout:boundingBox>
              <layout:position layout:x="390" layout:y="350"/>
              <layout:dimensions layout:height="20" layout:width="20"/>
            </layout:boundingBox>
            <layout:listOfSpeciesReferenceGlyphs>
              <layout:speciesReferenceGlyph layout:id="Glyph__o_uptake__substrate__dummy" layout:role="substrate" layout:speciesGlyph="Glyph__dummy">
                <layout:curve>
                  <layout:listOfCurveSegments>
                    <layout:curveSegment xsi:type="LineSegment">
                      <layout:start layout:x="265" layout:y="395"/>
                      <layout:end layout:x="400" layout:y="360"/>
                    </layout:curveSegment>
                  </layout:listOfCurveSegments>
                </layout:curve>
              </layout:speciesReferenceGlyph>
            </layout:listOfSpeciesReferenceGlyphs>
          </layout:reactionGlyph>
        </layout:listOfReactionGlyphs>
        <layout:listOfTextGlyphs>
          <layout:textGlyph layout:graphicalObject="Glyph__Cell" layout:id="TextGlyph__Cell" layout:text="Cell">
            <layout:boundingBox>
              <layout:position layout:x="40" layout:y="0"/>
              <layout:dimensions layout:height="410" layout:width="770"/>
            </layout:boundingBox>
          </layout:textGlyph>
          <layout:textGlyph layout:graphicalObject="Glyph__O2" layout:id="TextGlyph__O2" layout:text="O2">
            <layout:boundingBox>
              <layout:position layout:x="50" layout:y="180"/>
              <layout:dimensions layout:height="30" layout:width="100"/>
            </layout:boundingBox>
          </layout:textGlyph>
          <layout:textGlyph layout:graphicalObject="Glyph__Ac" layout:id="TextGlyph__Ac" layout:text="Ac">
            <layout:boundingBox>
              <layout:position layout:x="120" layout:y="110"/>
              <layout:dimensions layout:height="30" layout:width="100"/>
            </layout:boundingBox>
          </layout:textGlyph>
          <layout:textGlyph layout:graphicalObject="Glyph__Glcxt" layout:id="TextGlyph__Glcxt" layout:text="Glcxt">
            <layout:boundingBox>
              <layout:position layout:x="340" layout:y="180"/>
              <layout:dimensions layout:height="30" layout:width="100"/>
            </layout:boundingBox>
          </layout:textGlyph>
          <layout:textGlyph layout:graphicalObject="Glyph__C1" layout:id="TextGlyph__C1" layout:text="C1">
            <layout:boundingBox>
              <layout:position layout:x="545" layout:y="10"/>
              <layout:dimensions layout:height="40" layout:width="80"/>
            </layout:boundingBox>
          </layout:textGlyph>
          <layout:textGlyph layout:graphicalObject="Glyph__C2" layout:id="TextGlyph__C2" layout:text="C2">
            <layout:boundingBox>
              <layout:position layout:x="210" layout:y="170"/>
              <layout:dimensions layout:height="40" layout:width="80"/>
            </layout:boundingBox>
          </layout:textGlyph>
          <layout:textGlyph layout:graphicalObject="Glyph__rateOfV1" layout:id="TextGlyph__rateOfV1" layout:text="rateOfV1">
            <layout:boundingBox>
              <layout:position layout:x="135" layout:y="260"/>
              <layout:dimensions layout:height="30" layout:width="30"/>
            </layout:boundingBox>
          </layout:textGlyph>
          <layout:textGlyph layout:graphicalObject="Glyph__rateOfV2" layout:id="TextGlyph__rateOfV2" layout:text="rateOfV2">
            <layout:boundingBox>
              <layout:position layout:x="190" layout:y="260"/>
              <layout:dimensions layout:height="30" layout:width="30"/>
            </layout:boundingBox>
          </layout:textGlyph>
          <layout:textGlyph layout:graphicalObject="Glyph__rateOfV3" layout:id="TextGlyph__rateOfV3" layout:text="rateOfV3">
            <layout:boundingBox>
              <layout:position layout:x="240" layout:y="260"/>
              <layout:dimensions layout:height="30" layout:width="30"/>
            </layout:boundingBox>
          </layout:textGlyph>
          <layout:textGlyph layout:graphicalObject="Glyph__rateOfV4" layout:id="TextGlyph__rateOfV4" layout:text="rateOfV4">
            <layout:boundingBox>
              <layout:position layout:x="290" layout:y="260"/>
              <layout:dimensions layout:height="30" layout:width="30"/>
            </layout:boundingBox>
          </layout:textGlyph>
          <layout:textGlyph layout:graphicalObject="Glyph__v1" layout:id="TextGlyph__v1" layout:text="v1">
            <layout:boundingBox>
              <layout:position layout:x="145" layout:y="350"/>
              <layout:dimensions layout:height="20" layout:width="20"/>
            </layout:boundingBox>
          </layout:textGlyph>
          <layout:textGlyph layout:graphicalObject="Glyph__v2" layout:id="TextGlyph__v2" layout:text="v2">
            <layout:boundingBox>
              <layout:position layout:x="195" layout:y="350"/>
              <layout:dimensions layout:height="20" layout:width="20"/>
            </layout:boundingBox>
          </layout:textGlyph>
          <layout:textGlyph layout:graphicalObject="Glyph__v3" layout:id="TextGlyph__v3" layout:text="v3">
            <layout:boundingBox>
              <layout:position layout:x="250" layout:y="350"/>
              <layout:dimensions layout:height="20" layout:width="20"/>
            </layout:boundingBox>
          </layout:textGlyph>
          <layout:textGlyph layout:graphicalObject="Glyph__v4" layout:id="TextGlyph__v4" layout:text="v4">
            <layout:boundingBox>
              <layout:position layout:x="300" layout:y="350"/>
              <layout:dimensions layout:height="20" layout:width="20"/>
            </layout:boundingBox>
          </layout:textGlyph>
          <layout:textGlyph layout:graphicalObject="Glyph__dummy" layout:id="TextGlyph__dummy" layout:text="dummy">
            <layout:boundingBox>
              <layout:position layout:x="220" layout:y="380"/>
              <layout:dimensions layout:height="30" layout:width="90"/>
            </layout:boundingBox>
          </layout:textGlyph>
          <layout:textGlyph layout:graphicalObject="Glyph__max_v1" layout:id="TextGlyph__max_v1" layout:text="max_v1">
            <layout:boundingBox>
              <layout:position layout:x="500" layout:y="70"/>
              <layout:dimensions layout:height="30" layout:width="30"/>
            </layout:boundingBox>
          </layout:textGlyph>
          <layout:textGlyph layout:graphicalObject="Glyph__max_v2" layout:id="TextGlyph__max_v2" layout:text="max_v2">
            <layout:boundingBox>
              <layout:position layout:x="550" layout:y="70"/>
              <layout:dimensions layout:height="30" layout:width="30"/>
            </layout:boundingBox>
          </layout:textGlyph>
          <layout:textGlyph layout:graphicalObject="Glyph__o2_transport" layout:id="TextGlyph__o2_transport" layout:text="o2_transport">
            <layout:boundingBox>
              <layout:position layout:x="90" layout:y="230"/>
              <layout:dimensions layout:height="20" layout:width="20"/>
            </layout:boundingBox>
          </layout:textGlyph>
          <layout:textGlyph layout:graphicalObject="Glyph__" layout:id="TextGlyph__" layout:text="">
            <layout:boundingBox>
              <layout:position layout:x="60" layout:y="170"/>
              <layout:dimensions layout:height="30" layout:width="30"/>
            </layout:boundingBox>
          </layout:textGlyph>
          <layout:textGlyph layout:graphicalObject="Glyph__max_v3" layout:id="TextGlyph__max_v3" layout:text="max_v3">
            <layout:boundingBox>
              <layout:position layout:x="600" layout:y="70"/>
              <layout:dimensions layout:height="30" layout:width="30"/>
            </layout:boundingBox>
          </layout:textGlyph>
          <layout:textGlyph layout:graphicalObject="Glyph__max_v4" layout:id="TextGlyph__max_v4" layout:text="max_v4">
            <layout:boundingBox>
              <layout:position layout:x="650" layout:y="70"/>
              <layout:dimensions layout:height="30" layout:width="30"/>
            </layout:boundingBox>
          </layout:textGlyph>
          <layout:textGlyph layout:graphicalObject="Glyph__X" layout:id="TextGlyph__X" layout:text="X">
            <layout:boundingBox>
              <layout:position layout:x="260" layout:y="110"/>
              <layout:dimensions layout:height="30" layout:width="100"/>
            </layout:boundingBox>
          </layout:textGlyph>
          <layout:textGlyph layout:graphicalObject="Glyph__g_uptake" layout:id="TextGlyph__g_uptake" layout:text="g_uptake">
            <layout:boundingBox>
              <layout:position layout:x="340" layout:y="350"/>
              <layout:dimensions layout:height="20" layout:width="20"/>
            </layout:boundingBox>
          </layout:textGlyph>
          <layout:textGlyph layout:graphicalObject="Glyph__g_rate_uptake" layout:id="TextGlyph__g_rate_uptake" layout:text="g_rate_uptake">
            <layout:boundingBox>
              <layout:position layout:x="340" layout:y="260"/>
              <layout:dimensions layout:height="30" layout:width="30"/>
            </layout:boundingBox>
          </layout:textGlyph>
          <layout:textGlyph layout:graphicalObject="Glyph__g_uptake_max" layout:id="TextGlyph__g_uptake_max" layout:text="g_uptake_max">
            <layout:boundingBox>
              <layout:position layout:x="375" layout:y="15"/>
              <layout:dimensions layout:height="30" layout:width="30"/>
            </layout:boundingBox>
          </layout:textGlyph>
          <layout:textGlyph layout:graphicalObject="Glyph__rule0" layout:id="TextGlyph__rule0" layout:text="rule0">
            <layout:boundingBox>
              <layout:position layout:x="365" layout:y="100"/>
              <layout:dimensions layout:height="50" layout:width="50"/>
            </layout:boundingBox>
          </layout:textGlyph>
          <layout:textGlyph layout:graphicalObject="Glyph__o_uptake" layout:id="TextGlyph__o_uptake" layout:text="o_uptake">
            <layout:boundingBox>
              <layout:position layout:x="390" layout:y="350"/>
              <layout:dimensions layout:height="20" layout:width="20"/>
            </layout:boundingBox>
          </layout:textGlyph>
          <layout:textGlyph layout:graphicalObject="Glyph__o_rate_uptake" layout:id="TextGlyph__o_rate_uptake" layout:text="o_rate_uptake">
            <layout:boundingBox>
              <layout:position layout:x="390" layout:y="260"/>
              <layout:dimensions layout:height="30" layout:width="30"/>
            </layout:boundingBox>
          </layout:textGlyph>
          <layout:textGlyph layout:graphicalObject="Glyph__rule1" layout:id="TextGlyph__rule1" layout:text="rule1">
            <layout:boundingBox>
              <layout:position layout:x="130" layout:y="300"/>
              <layout:dimensions layout:height="50" layout:width="50"/>
            </layout:boundingBox>
          </layout:textGlyph>
          <layout:textGlyph layout:graphicalObject="Glyph__rule2" layout:id="TextGlyph__rule2" layout:text="rule2">
            <layout:boundingBox>
              <layout:position layout:x="180" layout:y="300"/>
              <layout:dimensions layout:height="50" layout:width="50"/>
            </layout:boundingBox>
          </layout:textGlyph>
          <layout:textGlyph layout:graphicalObject="Glyph__rule3" layout:id="TextGlyph__rule3" layout:text="rule3">
            <layout:boundingBox>
              <layout:position layout:x="230" layout:y="300"/>
              <layout:dimensions layout:height="50" layout:width="50"/>
            </layout:boundingBox>
          </layout:textGlyph>
          <layout:textGlyph layout:graphicalObject="Glyph__rule4" layout:id="TextGlyph__rule4" layout:text="rule4">
            <layout:boundingBox>
              <layout:position layout:x="280" layout:y="300"/>
              <layout:dimensions layout:height="50" layout:width="50"/>
            </layout:boundingBox>
          </layout:textGlyph>
          <layout:textGlyph layout:graphicalObject="Glyph__rule5" layout:id="TextGlyph__rule5" layout:text="rule5">
            <layout:boundingBox>
              <layout:position layout:x="330" layout:y="300"/>
              <layout:dimensions layout:height="50" layout:width="50"/>
            </layout:boundingBox>
          </layout:textGlyph>
          <layout:textGlyph layout:graphicalObject="Glyph__rule6" layout:id="TextGlyph__rule6" layout:text="rule6">
            <layout:boundingBox>
              <layout:position layout:x="380" layout:y="300"/>
              <layout:dimensions layout:height="50" layout:width="50"/>
            </layout:boundingBox>
          </layout:textGlyph>
        </layout:listOfTextGlyphs>
      </layout:layout>
    </layout:listOfLayouts>
            <listOfCompartments>
      <compartment constant="false" id="Cell" size="1" spatialDimensions="3"/>
    </listOfCompartments>
    <listOfSpecies>
      <species boundaryCondition="false" compartment="Cell" constant="false" hasOnlySubstanceUnits="true" id="O2" initialAmount="0.21" metaid="iBioSim1">
        <comp:listOfReplacedElements xmlns:comp="http://www.sbml.org/sbml/level3/version1/comp/version1">
          <comp:replacedElement comp:portRef="input__O2_out" comp:submodelRef="C2"/>
          <comp:replacedElement comp:portRef="input__O2" comp:submodelRef="C2"/>
        </comp:listOfReplacedElements>
      </species>
      <species boundaryCondition="false" compartment="Cell" constant="false" hasOnlySubstanceUnits="true" id="Ac" initialAmount="0.4" metaid="iBioSim3">
        <comp:listOfReplacedElements xmlns:comp="http://www.sbml.org/sbml/level3/version1/comp/version1">
          <comp:replacedElement comp:portRef="input__Ac" comp:submodelRef="C2"/>
        </comp:listOfReplacedElements>
      </species>
      <species boundaryCondition="false" compartment="Cell" constant="false" hasOnlySubstanceUnits="true" id="Glcxt" initialAmount="10.8" metaid="iBioSim5">
        <comp:listOfReplacedElements xmlns:comp="http://www.sbml.org/sbml/level3/version1/comp/version1">
          <comp:replacedElement comp:portRef="input__Glcxt_out" comp:submodelRef="C2"/>
          <comp:replacedElement comp:portRef="input__Glcxt" comp:submodelRef="C2"/>
        </comp:listOfReplacedElements>
      </species>
      <species boundaryCondition="false" compartment="Cell" constant="false" hasOnlySubstanceUnits="true" id="dummy" initialAmount="0" metaid="iBioSim16"/>
      <species boundaryCondition="false" compartment="Cell" constant="false" hasOnlySubstanceUnits="true" id="X" initialAmount="0.001" metaid="iBioSim21">
        <comp:listOfReplacedElements xmlns:comp="http://www.sbml.org/sbml/level3/version1/comp/version1">
          <comp:replacedElement comp:portRef="input__X" comp:submodelRef="C2"/>
        </comp:listOfReplacedElements>
      </species>
    </listOfSpecies>
    <listOfParameters>
      <parameter constant="false" id="rateOfV1" metaid="iBioSim8" value="0">
        <comp:listOfReplacedElements xmlns:comp="http://www.sbml.org/sbml/level3/version1/comp/version1">
          <comp:replacedElement comp:portRef="input__rateOfV1" comp:submodelRef="C2"/>
        </comp:listOfReplacedElements>
      </parameter>
      <parameter constant="false" id="rateOfV2" metaid="iBioSim9" value="0">
        <comp:listOfReplacedElements xmlns:comp="http://www.sbml.org/sbml/level3/version1/comp/version1">
          <comp:replacedElement comp:portRef="input__rateOfV2" comp:submodelRef="C2"/>
        </comp:listOfReplacedElements>
      </parameter>
      <parameter constant="false" id="rateOfV3" metaid="iBioSim10" value="0">
        <comp:listOfReplacedElements xmlns:comp="http://www.sbml.org/sbml/level3/version1/comp/version1">
          <comp:replacedElement comp:portRef="input__rateOfV3" comp:submodelRef="C2"/>
        </comp:listOfReplacedElements>
      </parameter>
      <parameter constant="false" id="rateOfV4" metaid="iBioSim11" value="0">
        <comp:listOfReplacedElements xmlns:comp="http://www.sbml.org/sbml/level3/version1/comp/version1">
          <comp:replacedElement comp:portRef="input__rateOfV4" comp:submodelRef="C2"/>
        </comp:listOfReplacedElements>
      </parameter>
      <parameter constant="false" id="max_v1" metaid="iBioSim17" value="10">
        <comp:listOfReplacedElements xmlns:comp="http://www.sbml.org/sbml/level3/version1/comp/version1">
          <comp:replacedElement comp:portRef="input__max_v1" comp:submodelRef="C1"/>
        </comp:listOfReplacedElements>
      </parameter>
      <parameter constant="false" id="max_v2" metaid="iBioSim18" value="10">
        <comp:listOfReplacedElements xmlns:comp="http://www.sbml.org/sbml/level3/version1/comp/version1">
          <comp:replacedElement comp:portRef="input__max_v2" comp:submodelRef="C1"/>
        </comp:listOfReplacedElements>
      </parameter>
      <parameter constant="true" id="Km" metaid="iBioSim6" value="0.015"/>
      <parameter constant="false" id="max_v3" metaid="iBioSim27" value="10">
        <comp:listOfReplacedElements xmlns:comp="http://www.sbml.org/sbml/level3/version1/comp/version1">
          <comp:replacedElement comp:portRef="input__max_v3" comp:submodelRef="C1"/>
        </comp:listOfReplacedElements>
      </parameter>
      <parameter constant="false" id="max_v4" metaid="iBioSim28" value="10">
        <comp:listOfReplacedElements xmlns:comp="http://www.sbml.org/sbml/level3/version1/comp/version1">
          <comp:replacedElement comp:portRef="input__max_v4" comp:submodelRef="C1"/>
        </comp:listOfReplacedElements>
      </parameter>
      <parameter constant="true" id="dt" metaid="iBioSim2" value="0.04"/>
      <parameter constant="false" id="g_rate_uptake" metaid="iBioSim48" value="0">
        <comp:listOfReplacedElements xmlns:comp="http://www.sbml.org/sbml/level3/version1/comp/version1">
          <comp:replacedElement comp:portRef="input__g_rate_uptake" comp:submodelRef="C2"/>
        </comp:listOfReplacedElements>
      </parameter>
      <parameter constant="false" id="g_uptake_max" metaid="iBioSim49" value="0">
        <comp:listOfReplacedElements xmlns:comp="http://www.sbml.org/sbml/level3/version1/comp/version1">
          <comp:replacedElement comp:portRef="input__g_uptake_max" comp:submodelRef="C1"/>
        </comp:listOfReplacedElements>
      </parameter>
      <parameter constant="false" id="o_rate_uptake" metaid="iBioSim50" value="0">
        <comp:listOfReplacedElements xmlns:comp="http://www.sbml.org/sbml/level3/version1/comp/version1">
          <comp:replacedElement comp:portRef="input__o_rate_uptake" comp:submodelRef="C2"/>
        </comp:listOfReplacedElements>
      </parameter>
      <parameter constant="true" id="c" metaid="iBioSim4" value="1"/>
    </listOfParameters>
        <listOfRules>
      <assignmentRule metaid="rule0" variable="g_uptake_max">
        <math xmlns="http://www.w3.org/1998/Math/MathML">        
          <apply>
            <divide/>
            <apply>
              <times/>
              <cn type="integer"> 10 </cn>
              <ci> Glcxt </ci>
            </apply>
            <apply>
              <plus/>
              <ci> Km </ci>
              <ci> Glcxt </ci>
            </apply>
          </apply>
        </math>
            </assignmentRule>
      <assignmentRule metaid="rule1" variable="rateOfV1">
        <math xmlns="http://www.w3.org/1998/Math/MathML">        
          <ci> v1 </ci>
        </math>
            </assignmentRule>
      <assignmentRule metaid="rule2" variable="rateOfV2">
        <math xmlns="http://www.w3.org/1998/Math/MathML">        
          <ci> v2 </ci>
        </math>
            </assignmentRule>
      <assignmentRule metaid="rule3" variable="rateOfV3">
        <math xmlns="http://www.w3.org/1998/Math/MathML">        
          <ci> v3 </ci>
        </math>
            </assignmentRule>
      <assignmentRule metaid="rule4" variable="rateOfV4">
        <math xmlns="http://www.w3.org/1998/Math/MathML">        
          <ci> v4 </ci>
        </math>
            </assignmentRule>
      <assignmentRule metaid="rule5" variable="g_rate_uptake">
        <math xmlns="http://www.w3.org/1998/Math/MathML">        
          <ci> g_uptake </ci>
        </math>
            </assignmentRule>
      <assignmentRule metaid="rule6" variable="o_rate_uptake">
        <math xmlns="http://www.w3.org/1998/Math/MathML">        
          <ci> o_uptake </ci>
        </math>
            </assignmentRule>
    </listOfRules>
        <listOfReactions>
      <reaction compartment="Cell" fast="false" id="v4" metaid="iBioSim15" reversible="false">
        <comp:replacedBy xmlns:comp="http://www.sbml.org/sbml/level3/version1/comp/version1" comp:portRef="reaction__v4" comp:submodelRef="C1"/>
        <listOfReactants>
          <speciesReference constant="true" species="dummy" stoichiometry="1"/>
        </listOfReactants>
                        <kineticLaw>
          <math xmlns="http://www.w3.org/1998/Math/MathML">          
            <ci> kf </ci>
          </math>
                  <listOfLocalParameters>
            <localParameter id="kf" value="0.1"/>
            <localParameter id="kr" value="1"/>
          </listOfLocalParameters>
        </kineticLaw>
      </reaction>
      <reaction compartment="Cell" fast="false" id="v2" metaid="iBioSim13" reversible="false">
        <comp:replacedBy xmlns:comp="http://www.sbml.org/sbml/level3/version1/comp/version1" comp:portRef="reaction__v2" comp:submodelRef="C1"/>
        <listOfReactants>
          <speciesReference constant="true" species="dummy" stoichiometry="1"/>
        </listOfReactants>
                        <kineticLaw>
          <math xmlns="http://www.w3.org/1998/Math/MathML">          
            <ci> kf </ci>
          </math>
                  <listOfLocalParameters>
            <localParameter id="kf" value="0.1"/>
            <localParameter id="kr" value="1"/>
          </listOfLocalParameters>
        </kineticLaw>
      </reaction>
      <reaction compartment="Cell" fast="false" id="v3" metaid="iBioSim14" reversible="false">
        <comp:replacedBy xmlns:comp="http://www.sbml.org/sbml/level3/version1/comp/version1" comp:portRef="reaction__v3" comp:submodelRef="C1"/>
        <listOfReactants>
          <speciesReference constant="true" species="dummy" stoichiometry="1"/>
        </listOfReactants>
                        <kineticLaw>
          <math xmlns="http://www.w3.org/1998/Math/MathML">          
            <ci> kf </ci>
          </math>
                  <listOfLocalParameters>
            <localParameter id="kf" value="0.1"/>
            <localParameter id="kr" value="1"/>
          </listOfLocalParameters>
        </kineticLaw>
      </reaction>
      <reaction compartment="Cell" fast="false" id="g_uptake" metaid="iBioSim19" reversible="false">
        <listOfReactants>
          <speciesReference constant="true" species="dummy" stoichiometry="1"/>
        </listOfReactants>
                        <kineticLaw>
          <math xmlns="http://www.w3.org/1998/Math/MathML">          
            <ci> kf </ci>
          </math>
                  <listOfLocalParameters>
            <localParameter id="kf" value="0.1"/>
            <localParameter id="kr" value="1"/>
          </listOfLocalParameters>
        </kineticLaw>
      </reaction>
      <reaction compartment="Cell" fast="false" id="o_uptake" metaid="iBioSim22" reversible="false">
        <listOfReactants>
          <speciesReference constant="true" species="dummy" stoichiometry="1"/>
        </listOfReactants>
                        <kineticLaw>
          <math xmlns="http://www.w3.org/1998/Math/MathML">          
            <ci> kf </ci>
          </math>
                  <listOfLocalParameters>
            <localParameter id="kf" value="0.1"/>
            <localParameter id="kr" value="1"/>
          </listOfLocalParameters>
        </kineticLaw>
      </reaction>
      <reaction compartment="Cell" fast="false" id="v1" metaid="iBioSim12" reversible="false">
        <comp:replacedBy xmlns:comp="http://www.sbml.org/sbml/level3/version1/comp/version1" comp:portRef="reaction__v1" comp:submodelRef="C1"/>
        <listOfReactants>
          <speciesReference constant="true" species="dummy" stoichiometry="1"/>
        </listOfReactants>
                        <kineticLaw>
          <math xmlns="http://www.w3.org/1998/Math/MathML">          
            <ci> kf </ci>
          </math>
                  <listOfLocalParameters>
            <localParameter id="kf" value="0.1"/>
            <localParameter id="kr" value="1"/>
          </listOfLocalParameters>
        </kineticLaw>
      </reaction>
      <reaction compartment="Cell" fast="false" id="o2_transport" metaid="iBioSim23" reversible="false">
                <listOfProducts>
          <speciesReference constant="true" species="O2" stoichiometry="1"/>
        </listOfProducts>
                <kineticLaw>
          <math xmlns="http://www.w3.org/1998/Math/MathML">          
            <apply>
              <times/>
              <ci> kLa </ci>
              <apply>
                <minus/>
                <cn> 0.21 </cn>
                <ci> O2 </ci>
              </apply>
            </apply>
          </math>
                  <listOfLocalParameters>
            <localParameter id="kLa" metaid="R8___kLa" value="7.5"/>
          </listOfLocalParameters>
        </kineticLaw>
      </reaction>
    </listOfReactions>
      </model>
</sbml>